pelican/plugins/icons/__init__.py
pelican/plugins/icons/docutils.py
pelican/plugins/icons/markdown.py
pelican/plugins/icons/utils.py
pelican_icons-1.0.0b0.dist-info/METADATA
pelican_icons-1.0.0b0.dist-info/WHEEL
pelican_icons-1.0.0b0.dist-info/RECORD
